blackfox/EncoderTesting.py
blackfox/__init__.py
blackfox/black_fox.py
blackfox/csv_log_writer.py
blackfox/log_writer.py
blackfox/setup.py
blackfox/test.py
blackfox/test_BlackFoxPython.py
blackfox/validation.py
blackfox-6.1.1.dist-info/METADATA
blackfox-6.1.1.dist-info/WHEEL
blackfox-6.1.1.dist-info/top_level.txt
blackfox-6.1.1.dist-info/RECORD
