Metadata-Version: 2.1
Name: blackfox
Version: 6.1.1
Summary: BlackFox client
Home-page: https://github.com/vodena/BlackFoxPython
Author: Vodena
Author-email: UNKNOWN
License: UNKNOWN
Keywords: BlackFox
Platform: UNKNOWN
Requires-Dist: urllib3 (>=1.15)
Requires-Dist: six (>=1.10)
Requires-Dist: certifi
Requires-Dist: python-dateutil
Requires-Dist: blackfox-restapi (>=6.1.1)
